digital_rf/__init__.py
digital_rf/_py_rf_write_hdf5.cp310-win_amd64.pyd
digital_rf/_version.py
digital_rf/digital_metadata.py
digital_rf/digital_rf_deprecated_hdf5.py
digital_rf/digital_rf_hdf5.py
digital_rf/drf_command.py
digital_rf/list_drf.py
digital_rf/mirror.py
digital_rf/ringbuffer.py
digital_rf/util.py
digital_rf/watchdog_drf.py
gr_digital_rf/__init__.py
gr_digital_rf/digital_rf_sink.py
gr_digital_rf/digital_rf_source.py
gr_digital_rf/raster.py
gr_digital_rf/vector.py
digital_rf-2.6.13.data/data/share/gnuradio/grc/blocks/gr_digital_rf.tree.yml
digital_rf-2.6.13.data/data/share/gnuradio/grc/blocks/gr_digital_rf_digital_rf_channel_sink.block.yml
digital_rf-2.6.13.data/data/share/gnuradio/grc/blocks/gr_digital_rf_digital_rf_channel_sink.xml
digital_rf-2.6.13.data/data/share/gnuradio/grc/blocks/gr_digital_rf_digital_rf_channel_source.block.yml
digital_rf-2.6.13.data/data/share/gnuradio/grc/blocks/gr_digital_rf_digital_rf_channel_source.xml
digital_rf-2.6.13.data/data/share/gnuradio/grc/blocks/gr_digital_rf_digital_rf_sink.block.yml
digital_rf-2.6.13.data/data/share/gnuradio/grc/blocks/gr_digital_rf_digital_rf_sink.xml
digital_rf-2.6.13.data/data/share/gnuradio/grc/blocks/gr_digital_rf_digital_rf_source.block.yml
digital_rf-2.6.13.data/data/share/gnuradio/grc/blocks/gr_digital_rf_digital_rf_source.xml
digital_rf-2.6.13.data/data/share/gnuradio/grc/blocks/gr_digital_rf_raster_aggregate.block.yml
digital_rf-2.6.13.data/data/share/gnuradio/grc/blocks/gr_digital_rf_raster_aggregate.xml
digital_rf-2.6.13.data/data/share/gnuradio/grc/blocks/gr_digital_rf_raster_chunk.block.yml
digital_rf-2.6.13.data/data/share/gnuradio/grc/blocks/gr_digital_rf_raster_chunk.xml
digital_rf-2.6.13.data/data/share/gnuradio/grc/blocks/gr_digital_rf_raster_select.block.yml
digital_rf-2.6.13.data/data/share/gnuradio/grc/blocks/gr_digital_rf_raster_select.xml
digital_rf-2.6.13.data/data/share/gnuradio/grc/blocks/gr_digital_rf_raster_tag.block.yml
digital_rf-2.6.13.dist-info/METADATA
digital_rf-2.6.13.dist-info/WHEEL
digital_rf-2.6.13.dist-info/entry_points.txt
digital_rf-2.6.13.dist-info/licenses/AUTHORS
digital_rf-2.6.13.dist-info/licenses/LICENSE
digital_rf-2.6.13.dist-info/RECORD
