Metadata-Version: 2.1
Name: digital_rf
Version: 2.6.13
Summary: Library for reading and writing time-tagged RF data in the Digital RF format
Keywords: hdf5,radio,rf
Author-Email: Bill Rideout <brideout@mit.edu>, Juha Vierinen <jvi019@uit.no>, Frank Lind <fdlind@mit.edu>, Ryan Volz <rvolz@mit.edu>, John Swoboda <swoboj@mit.edu>
Maintainer-Email: Ryan Volz <rvolz@mit.edu>
License: This software, unless otherwise noted, is licensed under the BSD 3-clause "New"
Classifier: Development Status :: 5 - Production/Stable
Classifier: Environment :: Console
Classifier: Intended Audience :: Science/Research
Classifier: Intended Audience :: Developers
Classifier: License :: OSI Approved :: BSD License
Classifier: Operating System :: OS Independent
Classifier: Programming Language :: C
Classifier: Programming Language :: Python
Classifier: Programming Language :: Python :: 3
Classifier: Programming Language :: Python :: 3 :: Only
Classifier: Programming Language :: Python :: 3.8
Classifier: Programming Language :: Python :: 3.9
Classifier: Programming Language :: Python :: 3.10
Classifier: Programming Language :: Python :: 3.11
Classifier: Programming Language :: Python :: 3.12
Classifier: Programming Language :: Python :: 3.13
Classifier: Topic :: Scientific/Engineering
Project-URL: Homepage, https://github.com/MITHaystack/digital_rf
Project-URL: Bug Tracker, https://github.com/MITHaystack/digital_rf/issues
Project-URL: Discussions, https://github.com/MITHaystack/digital_rf/discussions
Project-URL: Changelog, https://github.com/MITHaystack/digital_rf/releases
Requires-Python: >=3.8
Requires-Dist: h5py
Requires-Dist: numpy
Requires-Dist: packaging
Requires-Dist: python-dateutil
Requires-Dist: six
Requires-Dist: watchdog
Provides-Extra: test
Requires-Dist: pytest>=6; extra == "test"
Requires-Dist: pytest-cov>=3; extra == "test"
Provides-Extra: dev
Requires-Dist: pytest>=6; extra == "dev"
Requires-Dist: pytest-cov>=3; extra == "dev"
Provides-Extra: dataframe
Requires-Dist: pandas; extra == "dataframe"
Provides-Extra: plot
Requires-Dist: matplotlib; extra == "plot"
Requires-Dist: scipy; extra == "plot"
Provides-Extra: sound
Requires-Dist: sounddevice; extra == "sound"
Provides-Extra: all
Requires-Dist: matplotlib; extra == "all"
Requires-Dist: pandas; extra == "all"
Requires-Dist: scipy; extra == "all"
Requires-Dist: sounddevice; extra == "all"
